simtk/__init__.py
simtk-0.1.0.dist-info/WHEEL
simtk-0.1.0.dist-info/METADATA
simtk-0.1.0.dist-info/RECORD
