Metadata-Version: 2.1
Name: simtk
Version: 0.1.0
Summary: sim: structured illumination microscopy
Home-page: https://github.com/sim-reconstruction/simtk
License: UNKNOWN
Author: Matt McCormick
Author-email: matt.mccormick@kitware.com
Classifier: License :: OSI Approved :: Apache Software License
